firewheel_repo_caida/__init__.py
firewheel_repo_caida/load/MANIFEST
firewheel_repo_caida/load/README.rst
firewheel_repo_caida/load/plugin.py
firewheel_repo_caida/parse/MANIFEST
firewheel_repo_caida/parse/README.rst
firewheel_repo_caida/parse/model_component_objects.py
firewheel_repo_caida/parse/plugin.py
firewheel_repo_caida/parse/INSTALL/tasks.yml
firewheel_repo_caida/parse/INSTALL/vars.yml
firewheel_repo_caida/prune/MANIFEST
firewheel_repo_caida/prune/README.rst
firewheel_repo_caida/prune/plugin.py
firewheel_repo_caida/save/MANIFEST
firewheel_repo_caida/save/README.rst
firewheel_repo_caida/save/plugin.py
firewheel_repo_caida/tests/topology/MANIFEST
firewheel_repo_caida/tests/topology/README.rst
firewheel_repo_caida/tests/topology/caida_10_hosts_pruned.png
firewheel_repo_caida/tests/topology/plugin.py
firewheel_repo_caida-1.0.0.dist-info/licenses/LICENSE
firewheel_repo_caida-1.0.0.dist-info/METADATA
firewheel_repo_caida-1.0.0.dist-info/WHEEL
firewheel_repo_caida-1.0.0.dist-info/entry_points.txt
firewheel_repo_caida-1.0.0.dist-info/top_level.txt
firewheel_repo_caida-1.0.0.dist-info/RECORD
