Metadata-Version: 2.4
Name: firewheel_repo_caida
Version: 1.0.0
Summary: This Model Component repository contains MCs related to using data from the Center for Applied Internet Data Analysis (CAIDA) to create Internet-realistic topologies for a FIREWHEEL experiment.
Author-email: FIREWHEEL Developers <firewheel@sandia.gov>
License: Apache License (2.0)
Project-URL: Homepage, https://www.sandia.gov/emulytics
Classifier: Development Status :: 5 - Production/Stable
Classifier: Environment :: Console
Classifier: Intended Audience :: Developers
Classifier: Intended Audience :: Information Technology
Classifier: Intended Audience :: Telecommunications Industry
Classifier: Intended Audience :: Science/Research
Classifier: Natural Language :: English
Classifier: Programming Language :: Python :: 3
Classifier: Programming Language :: Python :: 3.8
Classifier: Programming Language :: Python :: 3.9
Classifier: Programming Language :: Python :: 3.10
Classifier: Programming Language :: Python :: 3.11
Classifier: Programming Language :: Python :: 3.12
Classifier: Programming Language :: Python :: 3.13
Classifier: License :: OSI Approved :: Apache Software License
Classifier: Operating System :: OS Independent
Classifier: Topic :: Internet
Classifier: Topic :: Scientific/Engineering
Classifier: Topic :: Scientific/Engineering :: Information Analysis
Classifier: Topic :: Security
Classifier: Topic :: System :: Clustering
Classifier: Topic :: System :: Distributed Computing
Classifier: Topic :: System :: Emulators
Classifier: Topic :: System :: Networking
Classifier: Topic :: Utilities
Requires-Python: >=3.8
License-File: LICENSE
Requires-Dist: firewheel
Requires-Dist: pytricia
Provides-Extra: format
Requires-Dist: ruff==0.13.1; extra == "format"
Dynamic: license-file
